Topsis_Vishakha/__init__.py
Topsis_Vishakha/topsis.py
Topsis_Vishakha_102003704-1.0.4.dist-info/LICENSE.txt
Topsis_Vishakha_102003704-1.0.4.dist-info/METADATA
Topsis_Vishakha_102003704-1.0.4.dist-info/WHEEL
Topsis_Vishakha_102003704-1.0.4.dist-info/entry_points.txt
Topsis_Vishakha_102003704-1.0.4.dist-info/top_level.txt
Topsis_Vishakha_102003704-1.0.4.dist-info/RECORD
