Metadata-Version: 2.1
Name: Topsis-Vishakha-102003704
Version: 1.0.4
Summary: A package -> Calculates Topsis Score and Rank them accordingly
Author: Vishakha
Author-email: vvishakha_be20@thapar.edu
License: MIT
Keywords: python package VISHAKHA
Classifier: Programming Language :: Python
Classifier: License :: OSI Approved :: MIT License
Classifier: Operating System :: OS Independent
License-File: LICENSE.txt
Requires-Dist: pandas
